{
    "Projects":{
        "ProProjects" : [
            {
                "title":"CEMNY.COM",
                "client":"Chautauqua Energy Managment",
                "link": "http://cemny.com",
                "gitlink": "https://github.com/ChrsSampson/CEM",
                "image":"/img/cemny.png",
                "desc": "A static webpage rendered server side featuring several Javascript Libraries.",
                "tags":["Express","EJS","BootStrap 5"]  
            },
            {
                "title":"PingPlotter MultiViewer",
                "client":"Digitell Inc.",
                "link": "http://multiviewer.herokuapp.com/",
                "gitlink": "https://github.com/ChrsSampson/Express-Multiview-Server",
                "image": "/img/multiviewer.png",
                "desc": "An internal tool used to keep track of network health of large quantities of computers simultaneously",
                "tags":["Express","MongoDB","Authentication"]
            },
            {
                "title":"SelfStorageCompanies.org",
                "client":"Esteem Managment",
                "link": "https://selfstoragecompanies.org",
                "gitlink": "",
                "image": "/img/storage.png",
                "desc": "A site designed to combine 3 existing and outdated sites into one.",
                "tags": ["WIX"]
            },
            {
                "title":"JodyVankeuren.com",
                "client":"Jody Vankeuren",
                "link": "https://jodyvankeuren.com/",
                "gitlink": "https://github.com/ChrsSampson/Jody-portfolio",
                "image": "/img/art.png",
                "desc": "A simple art gallery showcasing a few pieces.",
                "tags": ["Baguette Box", "Responsive", "Vanilla JS"]
            },
            {
                "title":"StuckNode.com",
                "client": "Chris Sampson",
                "link": "http://stucknode.com",
                "gitlink": "https://github.com/ChrsSampson/React-Portfolio",
                "image": "/img/node.png",
                "desc": "Behind the scenes of of this portfolio.",
                "tags": ["React", "Styled Components", "React Hooks"]
            }
        ],
        "ProtoProjects" : [
            {
                "title" : "Rock, Paper, Scissors",
                "desc" : "A simple game made using Javascript objects",
                "link" : "https://chrssampson.github.io/RockPaperScissors/",
                "gitlink": "https://github.com/ChrsSampson/RockPaperScissors",
                "image" : "/img/game.png",
                "tags": ["Vanilla JS", "DOM"]
            },
            {
                "title" : "Flickr Photo Searcher",
                "desc" : "Single Page React App that Fetches Images From Flickr",
                "link" : "https://musing-hopper-67b6b9.netlify.app/",
                "gitlink": "https://github.com/ChrsSampson/React-Flickr-App",
                "image" : "/img/flickr.png",
                "tags": ["React", "Axios", "3rd Party API"]
            },
            {
                "title" : "Yelp Camp",
                "desc" : "A fake social media site based around campgrounds, currently incomplete",
                "link" : "",
                "gitlink": "https://github.com/ChrsSampson/YelpCamp",
                "image" : "/img/yelp.png",
                "tags": ["Express", "MongoDB", "Authentication"]
            },
            {
                "title" : "SQL School Rest API",
                "desc" : "A REST API capable of CRUD functionalitly on a SQL Database and respond with JSON data",
                "link" : "",
                "gitlink": "https://github.com/ChrsSampson/SQL-Rest-API",
                "image" : "/img/folder.png",
                "tags": ["SQLite", "RESTful Routes", "Express"]
            },
            {
                "title" : "SQL Library",
                "desc" : "An editable library database app made to practice SQL concepts",
                "link" : "",
                "gitlink": "https://github.com/ChrsSampson/SQL-Library",
                "image" : "/img/book.png",
                "tags": ["SQLite", "RESTful Routes", "PUG"]
            }
        ]
    },
    "About" : [
        {
            "name" : "Chris Sampson",
            "title": "Full Stack Developer",
            "tagline": "Design. Develop. Deploy",
            "bio": "Here's a little about me, I am a web developer currently living in New York with a background in Systems Administration and Virtualization. I am both driven and self-motivated and I am always trying new and experimental technologies and methods. I am my worst critic so I am constantly trying to better myself as a developer as I strive to create a better internet for all."
            
        }
    ],
    "Skills" : [
        "HTML5",
        "CSS3",
        "SASS",
        "JavaScript",
        "React",
        "Axios",
        "Fetch API",
        "Express",
        "Git",
        "MongoDB",
        "SQL",
        "Bootstrap 5",
        "Responsive Design",
        "Hosting",
        "Node",
        "PUG",
        "MERN Stack"
    ]
    
}